Packageimportant/__init__.py
Packageimportant/get_sla.py
Packageimportant/sla_deter.py
packageimportant-0.0.5.dist-info/METADATA
packageimportant-0.0.5.dist-info/WHEEL
packageimportant-0.0.5.dist-info/top_level.txt
packageimportant-0.0.5.dist-info/RECORD
