Metadata-Version: 2.1
Name: packageimportant
Version: 0.0.5
Author: Manas Royr
Author-email: manas@bbrio.in
License: MIT
Classifier: Programming Language :: Python :: 3
Classifier: License :: OSI Approved :: MIT License
Classifier: Operating System :: OS Independent
Requires-Dist: pandas
